wame/__init__.py
wame/engine.py
wame/interval.py
wame/pipeline.py
wame/scene.py
wame/settings.py
wame/color/__init__.py
wame/color/rgb.py
wame/color/values.py
wame/ui/__init__.py
wame/ui/button.py
wame/ui/frame.py
wame/ui/image.py
wame/ui/input.py
wame/ui/renderable.py
wame/ui/text.py
wame/utils/__init__.py
wame/utils/keys.py
wame/utils/tween.py
wame/vector/__init__.py
wame/vector/base.py
wame/vector/xy.py
wame/vector/xyz.py
wame_engine-0.7.0.dist-info/licenses/LICENSE
wame_engine-0.7.0.dist-info/METADATA
wame_engine-0.7.0.dist-info/WHEEL
wame_engine-0.7.0.dist-info/top_level.txt
wame_engine-0.7.0.dist-info/RECORD
