Metadata-Version: 2.4
Name: wame-engine
Version: 0.7.0
Summary: Wame Game Engine
Author-email: WilDev Studios <wildevstudios@gmail.com>
License-Expression: MIT
Project-URL: Homepage, https://github.com/WilDev-Studios/Wame
Keywords: python,pygame,wrapper,engine,game,opengl,2D,3D
Classifier: Development Status :: 4 - Beta
Classifier: Natural Language :: English
Classifier: Operating System :: OS Independent
Classifier: Programming Language :: Python
Classifier: Topic :: Games/Entertainment
Classifier: Topic :: Software Development :: Libraries :: pygame
Requires-Python: >=3.7
License-File: LICENSE
Requires-Dist: pygame
Requires-Dist: pyopengl
Requires-Dist: numpy
Dynamic: license-file
